flake8_modern_annotations/__init__.py
flake8_modern_annotations/checker.py
flake8_modern_annotations-1.6.0.dist-info/METADATA
flake8_modern_annotations-1.6.0.dist-info/WHEEL
flake8_modern_annotations-1.6.0.dist-info/entry_points.txt
flake8_modern_annotations-1.6.0.dist-info/top_level.txt
flake8_modern_annotations-1.6.0.dist-info/RECORD
