Metadata-Version: 2.1
Name: flake8-modern-annotations
Version: 1.6.0
Summary: Flake8 modern annotations validation
Author-email: Peter Linss <pypi@linss.com>
License: GNU Lesser General Public License v3
Project-URL: homepage, https://github.com/plinss/flake8-modern-annotations
Keywords: flake8,noqa
Classifier: Framework :: Flake8
Classifier: Environment :: Console
Classifier: Intended Audience :: Developers
Classifier: License :: OSI Approved :: GNU Lesser General Public License v3 or later (LGPLv3+)
Classifier: Programming Language :: Python
Classifier: Programming Language :: Python :: 3
Classifier: Programming Language :: Python :: 3.7
Classifier: Programming Language :: Python :: 3.8
Classifier: Programming Language :: Python :: 3.9
Classifier: Programming Language :: Python :: 3.10
Classifier: Programming Language :: Python :: 3.11
Classifier: Topic :: Software Development :: Libraries :: Python Modules
Classifier: Topic :: Software Development :: Quality Assurance
Requires-Python: >=3.7
Requires-Dist: flake8 <8.0,>=3.8.0
Requires-Dist: typing-extensions >=3.7.4.2
Requires-Dist: importlib-metadata <5.0.0,>=4.0.0 ; python_version < "3.8.0"
Provides-Extra: dev
Requires-Dist: mypy ; extra == 'dev'
Requires-Dist: flake8 <6.0.0,>=3.8.0 ; extra == 'dev'
Requires-Dist: flake8-annotations ; extra == 'dev'
Requires-Dist: flake8-bandit ; extra == 'dev'
Requires-Dist: flake8-bugbear ; extra == 'dev'
Requires-Dist: flake8-commas ; extra == 'dev'
Requires-Dist: flake8-comprehensions ; extra == 'dev'
Requires-Dist: flake8-continuation ; extra == 'dev'
Requires-Dist: flake8-datetimez ; extra == 'dev'
Requires-Dist: flake8-docstrings ; extra == 'dev'
Requires-Dist: flake8-import-order ; extra == 'dev'
Requires-Dist: flake8-literal ; extra == 'dev'
Requires-Dist: flake8-noqa ; extra == 'dev'
Requires-Dist: flake8-polyfill ; extra == 'dev'
Requires-Dist: flake8-pyproject ; extra == 'dev'
Requires-Dist: flake8-modern-annotations ; extra == 'dev'
Requires-Dist: flake8-requirements ; extra == 'dev'
Requires-Dist: flake8-typechecking-import ; extra == 'dev'
Requires-Dist: flake8-use-fstring ; extra == 'dev'
Requires-Dist: pep8-naming ; extra == 'dev'
Provides-Extra: test
